autograd_lib/__init__.py
autograd_lib/_version.py
autograd_lib/autograd_lib.py
autograd_lib/util.py
autograd_lib-0.0.7.dist-info/LICENSE
autograd_lib-0.0.7.dist-info/METADATA
autograd_lib-0.0.7.dist-info/WHEEL
autograd_lib-0.0.7.dist-info/top_level.txt
autograd_lib-0.0.7.dist-info/RECORD
