Metadata-Version: 2.1
Name: autograd-lib
Version: 0.0.7
Summary: Library to simplify autograd computations in PyTorch
Home-page: https://github.com/cybertronai/autograd-lib
Author: Yaroslav Bulatov, Kazuki Osawa
Author-email: yaroslavvb@gmail.com
License: UNKNOWN
Platform: UNKNOWN
Classifier: Programming Language :: Python :: 3
Classifier: License :: OSI Approved :: MIT License
Classifier: Operating System :: OS Independent
Requires-Python: >= 3.6
Requires-Dist: gin-config
Requires-Dist: seaborn
Requires-Dist: pytorch-lightning
